{"v":5,"entries":{"atoms-alert--default":{"type":"story","id":"atoms-alert--default","name":"Default","title":"Atoms/Alert","importPath":"./src/ui/atoms/Alert/Alert.stories.ts","componentPath":"./src/ui/atoms/Alert/Alert.component.ts","tags":["dev","test"]},"atoms-alert--error":{"type":"story","id":"atoms-alert--error","name":"Error","title":"Atoms/Alert","importPath":"./src/ui/atoms/Alert/Alert.stories.ts","componentPath":"./src/ui/atoms/Alert/Alert.component.ts","tags":["dev","test"]},"atoms-button--default":{"type":"story","id":"atoms-button--default","name":"Default","title":"Atoms/Button","importPath":"./src/ui/atoms/Button/Button.stories.ts","componentPath":"./src/ui/atoms/Button/Button.component.ts","tags":["dev","test"]},"atoms-button--loading":{"type":"story","id":"atoms-button--loading","name":"Loading","title":"Atoms/Button","importPath":"./src/ui/atoms/Button/Button.stories.ts","componentPath":"./src/ui/atoms/Button/Button.component.ts","tags":["dev","test"]},"atoms-iconbutton--default":{"type":"story","id":"atoms-iconbutton--default","name":"Default","title":"Atoms/IconButton","importPath":"./src/ui/atoms/IconButton/IconButton.stories.ts","componentPath":"./src/ui/atoms/IconButton/IconButton.component.ts","tags":["dev","test"]},"atoms-iconbutton--edit":{"type":"story","id":"atoms-iconbutton--edit","name":"Edit","title":"Atoms/IconButton","importPath":"./src/ui/atoms/IconButton/IconButton.stories.ts","componentPath":"./src/ui/atoms/IconButton/IconButton.component.ts","tags":["dev","test"]},"atoms-image--primary":{"type":"story","id":"atoms-image--primary","name":"Primary","title":"Atoms/Image","importPath":"./src/ui/atoms/Image/Image.stories.ts","componentPath":"./src/ui/atoms/Image/Image.component.ts","tags":["dev","test"]},"atoms-input--default":{"type":"story","id":"atoms-input--default","name":"Default","title":"Atoms/Input","importPath":"./src/ui/atoms/Input/Input.stories.ts","componentPath":"./src/ui/atoms/Input/Input.component.ts","tags":["dev","test"]},"atoms-input--checkbox":{"type":"story","id":"atoms-input--checkbox","name":"Checkbox","title":"Atoms/Input","importPath":"./src/ui/atoms/Input/Input.stories.ts","componentPath":"./src/ui/atoms/Input/Input.component.ts","tags":["dev","test"]},"atoms-link--default":{"type":"story","id":"atoms-link--default","name":"Default","title":"Atoms/Link","importPath":"./src/ui/atoms/Link/Link.stories.ts","componentPath":"./src/ui/atoms/Link/Link.component.ts","tags":["dev","test"]},"atoms-link--active":{"type":"story","id":"atoms-link--active","name":"Active","title":"Atoms/Link","importPath":"./src/ui/atoms/Link/Link.stories.ts","componentPath":"./src/ui/atoms/Link/Link.component.ts","tags":["dev","test"]},"atoms-loader--default":{"type":"story","id":"atoms-loader--default","name":"Default","title":"Atoms/Loader","importPath":"./src/ui/atoms/Loader/Loader.stories.ts","componentPath":"./src/ui/atoms/Loader/Loader.component.ts","tags":["dev","test"]},"atoms-todoitem--default":{"type":"story","id":"atoms-todoitem--default","name":"Default","title":"Atoms/TodoItem","importPath":"./src/ui/atoms/TodoItem/TodoItem.stories.ts","componentPath":"./src/ui/atoms/TodoItem/TodoItem.component.ts","tags":["dev","test"]},"atoms-todoitem--completed":{"type":"story","id":"atoms-todoitem--completed","name":"Completed","title":"Atoms/TodoItem","importPath":"./src/ui/atoms/TodoItem/TodoItem.stories.ts","componentPath":"./src/ui/atoms/TodoItem/TodoItem.component.ts","tags":["dev","test"]},"molecules-addtodoform--default":{"type":"story","id":"molecules-addtodoform--default","name":"Default","title":"Molecules/AddTodoForm","importPath":"./src/ui/molecules/AddTodoForm/AddTodoForm.stories.ts","componentPath":"./src/ui/molecules/AddTodoForm/AddTodoForm.component.ts","tags":["dev","test"]},"molecules-addtodoform--loading":{"type":"story","id":"molecules-addtodoform--loading","name":"Loading","title":"Molecules/AddTodoForm","importPath":"./src/ui/molecules/AddTodoForm/AddTodoForm.stories.ts","componentPath":"./src/ui/molecules/AddTodoForm/AddTodoForm.component.ts","tags":["dev","test"]},"molecules-filtergroup--primary":{"type":"story","id":"molecules-filtergroup--primary","name":"Primary","title":"Molecules/FilterGroup","importPath":"./src/ui/molecules/FilterGroup/FilterGroup.stories.ts","componentPath":"./src/ui/molecules/FilterGroup/FilterGroup.component.ts","tags":["dev","test"]},"molecules-filtergroup--empty":{"type":"story","id":"molecules-filtergroup--empty","name":"Empty","title":"Molecules/FilterGroup","importPath":"./src/ui/molecules/FilterGroup/FilterGroup.stories.ts","componentPath":"./src/ui/molecules/FilterGroup/FilterGroup.component.ts","tags":["dev","test"]},"molecules-todoitems--default":{"type":"story","id":"molecules-todoitems--default","name":"Default","title":"Molecules/TodoItems","importPath":"./src/ui/molecules/TodoItems/TodoItems.stories.ts","componentPath":"./src/ui/molecules/TodoItems/TodoItems.component.ts","tags":["dev","test"]},"molecules-todoitems--empty":{"type":"story","id":"molecules-todoitems--empty","name":"Empty","title":"Molecules/TodoItems","importPath":"./src/ui/molecules/TodoItems/TodoItems.stories.ts","componentPath":"./src/ui/molecules/TodoItems/TodoItems.component.ts","tags":["dev","test"]},"organisms-siteheader--default":{"type":"story","id":"organisms-siteheader--default","name":"Default","title":"Organisms/SiteHeader","importPath":"./src/ui/organisms/SiteHeader/SiteHeader.stories.ts","componentPath":"./src/ui/organisms/SiteHeader/SiteHeader.component.ts","tags":["dev","test"]},"organisms-siteheader--dark":{"type":"story","id":"organisms-siteheader--dark","name":"Dark","title":"Organisms/SiteHeader","importPath":"./src/ui/organisms/SiteHeader/SiteHeader.stories.ts","componentPath":"./src/ui/organisms/SiteHeader/SiteHeader.component.ts","tags":["dev","test"]},"organisms-todofilters--default":{"type":"story","id":"organisms-todofilters--default","name":"Default","title":"Organisms/TodoFilters","importPath":"./src/ui/organisms/TodoFilters/TodoFilters.stories.ts","componentPath":"./src/ui/organisms/TodoFilters/TodoFilters.component.ts","tags":["dev","test"]},"organisms-todofilters--empty":{"type":"story","id":"organisms-todofilters--empty","name":"Empty","title":"Organisms/TodoFilters","importPath":"./src/ui/organisms/TodoFilters/TodoFilters.stories.ts","componentPath":"./src/ui/organisms/TodoFilters/TodoFilters.component.ts","tags":["dev","test"]},"organisms-todolist--default":{"type":"story","id":"organisms-todolist--default","name":"Default","title":"Organisms/TodoList","importPath":"./src/ui/organisms/TodoList/TodoList.stories.ts","componentPath":"./src/ui/organisms/TodoList/TodoList.component.ts","tags":["dev","test"]},"organisms-todolist--empty":{"type":"story","id":"organisms-todolist--empty","name":"Empty","title":"Organisms/TodoList","importPath":"./src/ui/organisms/TodoList/TodoList.stories.ts","componentPath":"./src/ui/organisms/TodoList/TodoList.component.ts","tags":["dev","test"]},"organisms-todolist--loading":{"type":"story","id":"organisms-todolist--loading","name":"Loading","title":"Organisms/TodoList","importPath":"./src/ui/organisms/TodoList/TodoList.stories.ts","componentPath":"./src/ui/organisms/TodoList/TodoList.component.ts","tags":["dev","test"]},"skeletons-skeleton--default":{"type":"story","id":"skeletons-skeleton--default","name":"Default","title":"Skeletons/Skeleton","importPath":"./src/ui/skeletons/Skeleton/Skeleton.stories.ts","componentPath":"./src/ui/skeletons/Skeleton/Skeleton.component.ts","tags":["dev","test"]},"skeletons-skeleton--image":{"type":"story","id":"skeletons-skeleton--image","name":"Image","title":"Skeletons/Skeleton","importPath":"./src/ui/skeletons/Skeleton/Skeleton.stories.ts","componentPath":"./src/ui/skeletons/Skeleton/Skeleton.component.ts","tags":["dev","test"]},"skeletons-skeleton--avatar":{"type":"story","id":"skeletons-skeleton--avatar","name":"Avatar","title":"Skeletons/Skeleton","importPath":"./src/ui/skeletons/Skeleton/Skeleton.stories.ts","componentPath":"./src/ui/skeletons/Skeleton/Skeleton.component.ts","tags":["dev","test"]},"templates-layout--default":{"type":"story","id":"templates-layout--default","name":"Default","title":"Templates/Layout","importPath":"./src/ui/templates/Skeleton/Layout.stories.ts","componentPath":"./src/ui/templates/Skeleton/Layout.component.ts","tags":["dev","test"]}}}